mlagents_envs/__init__.py
mlagents_envs/base_env.py
mlagents_envs/communicator.py
mlagents_envs/env_utils.py
mlagents_envs/environment.py
mlagents_envs/exception.py
mlagents_envs/logging_util.py
mlagents_envs/mock_communicator.py
mlagents_envs/rpc_communicator.py
mlagents_envs/rpc_utils.py
mlagents_envs/timers.py
mlagents_envs/communicator_objects/__init__.py
mlagents_envs/communicator_objects/agent_action_pb2.py
mlagents_envs/communicator_objects/agent_action_pb2.pyi
mlagents_envs/communicator_objects/agent_info_action_pair_pb2.py
mlagents_envs/communicator_objects/agent_info_action_pair_pb2.pyi
mlagents_envs/communicator_objects/agent_info_pb2.py
mlagents_envs/communicator_objects/agent_info_pb2.pyi
mlagents_envs/communicator_objects/brain_parameters_pb2.py
mlagents_envs/communicator_objects/brain_parameters_pb2.pyi
mlagents_envs/communicator_objects/capabilities_pb2.py
mlagents_envs/communicator_objects/capabilities_pb2.pyi
mlagents_envs/communicator_objects/command_pb2.py
mlagents_envs/communicator_objects/command_pb2.pyi
mlagents_envs/communicator_objects/custom_reset_parameters_pb2.py
mlagents_envs/communicator_objects/custom_reset_parameters_pb2.pyi
mlagents_envs/communicator_objects/demonstration_meta_pb2.py
mlagents_envs/communicator_objects/demonstration_meta_pb2.pyi
mlagents_envs/communicator_objects/engine_configuration_pb2.py
mlagents_envs/communicator_objects/engine_configuration_pb2.pyi
mlagents_envs/communicator_objects/header_pb2.py
mlagents_envs/communicator_objects/header_pb2.pyi
mlagents_envs/communicator_objects/observation_pb2.py
mlagents_envs/communicator_objects/observation_pb2.pyi
mlagents_envs/communicator_objects/space_type_pb2.py
mlagents_envs/communicator_objects/space_type_pb2.pyi
mlagents_envs/communicator_objects/training_analytics_pb2.py
mlagents_envs/communicator_objects/training_analytics_pb2.pyi
mlagents_envs/communicator_objects/unity_input_pb2.py
mlagents_envs/communicator_objects/unity_input_pb2.pyi
mlgame3d_envs-0.2.0.dist-info/METADATA
mlgame3d_envs-0.2.0.dist-info/WHEEL
mlgame3d_envs-0.2.0.dist-info/top_level.txt
mlgame3d_envs-0.2.0.dist-info/RECORD
