Metadata-Version: 2.4
Name: mlgame3d-envs
Version: 0.2.0
Summary: Unity Machine Learning Agents Interface
Home-page: https://github.com/PAIA-Playful-AI-Arena/mlgame3d-envs
Author: PAIA-Tech
Author-email: service@paia-tech.com
Classifier: Intended Audience :: Developers
Classifier: Topic :: Scientific/Engineering :: Artificial Intelligence
Classifier: License :: OSI Approved :: Apache Software License
Classifier: Programming Language :: Python :: 3.11
Requires-Python: >=3.11
Requires-Dist: packaging
Requires-Dist: cloudpickle
Requires-Dist: grpcio>=1.11.0
Requires-Dist: Pillow>=4.2.1
Requires-Dist: protobuf<3.21,>=3.6
Requires-Dist: pyyaml>=3.1.0
Requires-Dist: gym>=0.21.0
Requires-Dist: pettingzoo>=1.23.0
Requires-Dist: numpy<2.0,>=1.26
Requires-Dist: filelock>=3.4.0
Dynamic: author
Dynamic: author-email
Dynamic: classifier
Dynamic: description
Dynamic: description-content-type
Dynamic: home-page
Dynamic: requires-dist
Dynamic: requires-python
Dynamic: summary
